xcon/__init__.py
xcon/conf.py
xcon/config.py
xcon/directory.py
xcon/exceptions.py
xcon/meta.json
xcon/provider.py
xcon/providers/__init__.py
xcon/providers/common.py
xcon/providers/dynamo.py
xcon/providers/environmental.py
xcon/providers/secrets_manager.py
xcon/providers/ssm_param_store.py
xcon/pytest_plugin.py
xcon/random_backup.py
xcon/serverless_files/__init__.py
xcon/serverless_files/cache-permissions.yml
xcon/serverless_files/config_manager/cache-table.yml
xcon/serverless_files/config_manager/change_handler.py
xcon/serverless_files/config_manager/change_handler.yml
xcon/serverless_files/config_manager/config_cache_all_access.yml
xcon/serverless_files/secrets-permissions.yml
xcon/serverless_files/ssm-permissions.yml
xcon/serverless_files/xcon-resources.js
xcon/types.py
xcon-1.1.1.dist-info/METADATA
xcon-1.1.1.dist-info/WHEEL
xcon-1.1.1.dist-info/entry_points.txt
xcon-1.1.1.dist-info/licenses/LICENSE
xcon-1.1.1.dist-info/RECORD
