Metadata-Version: 2.4
Name: xcon
Version: 1.1.1
Summary: Dynamic configuration retreiver.
License-File: LICENSE
Keywords: settings,configuration,lazy,boto,aws,secrets manager,param store,ssm
Author: Josh Orr
Author-email: josh@orr.blue
Requires-Python: >=3.11,<4.0
Classifier: License :: OSI Approved :: The Unlicense (Unlicense)
Classifier: Programming Language :: Python :: 3
Classifier: Programming Language :: Python :: 3.11
Classifier: Programming Language :: Python :: 3.12
Classifier: Programming Language :: Python :: 3.13
Classifier: Programming Language :: Python :: 3.14
Classifier: Topic :: Software Development :: Libraries :: Python Modules
Requires-Dist: ciso8601 (>=2.3.1,<3.0.0)
Requires-Dist: xbool (>=1.1.0,<2.0.0)
Requires-Dist: xboto (>=1.1.1,<2.0.0)
Requires-Dist: xinject (>=1.4.1,<2.0.0)
Requires-Dist: xloop (>=1.1.0,<2.0.0)
Requires-Dist: xsentinels (>=1.2.2,<2.0.0)
Requires-Dist: xsettings (>=1.4.0,<2.0.0)
Project-URL: Repository, https://github.com/xyngular/py-xcon
